djanbee/__init__.py
djanbee/main.py
djanbee/commands/__init__.py
djanbee/commands/configure/__init__.py
djanbee/commands/configure/configure_database_display.py
djanbee/commands/configure/configure_database_manager.py
djanbee/commands/configure/configure_settings_display.py
djanbee/commands/configure/configure_settings_manager.py
djanbee/commands/configure/container.py
djanbee/commands/configure/types.py
djanbee/commands/deploy/__init__.py
djanbee/commands/deploy/container.py
djanbee/commands/deploy/display.py
djanbee/commands/deploy/manager.py
djanbee/commands/launch/__init__.py
djanbee/commands/launch/container.py
djanbee/commands/launch/display.py
djanbee/commands/launch/manager.py
djanbee/commands/run/__init__.py
djanbee/commands/run/container.py
djanbee/commands/run/display.py
djanbee/commands/run/manager.py
djanbee/commands/setup/__init__.py
djanbee/commands/setup/container.py
djanbee/commands/setup/display.py
djanbee/commands/setup/manager.py
djanbee/core/__init__.py
djanbee/core/container.py
djanbee/managers/__init__.py
djanbee/managers/console_manager.py
djanbee/managers/database_manager.py
djanbee/managers/django_manager/__init__.py
djanbee/managers/django_manager/container.py
djanbee/managers/django_manager/state.py
djanbee/managers/django_manager/services/project_service.py
djanbee/managers/django_manager/services/project_service_display.py
djanbee/managers/django_manager/services/requirements_service.py
djanbee/managers/django_manager/services/requirements_service_display.py
djanbee/managers/django_manager/services/settings_service.py
djanbee/managers/django_manager/services/settings_service_display.py
djanbee/managers/django_manager/services/venv_service.py
djanbee/managers/django_manager/services/venv_service_display.py
djanbee/managers/django_manager/services/settings_operations/allowed_hosts_handler.py
djanbee/managers/django_manager/services/settings_operations/allowed_hosts_handler_display.py
django_djanbee-0.1.0.dist-info/licenses/LICENSE
django_djanbee-0.1.0.dist-info/METADATA
django_djanbee-0.1.0.dist-info/WHEEL
django_djanbee-0.1.0.dist-info/entry_points.txt
django_djanbee-0.1.0.dist-info/top_level.txt
django_djanbee-0.1.0.dist-info/RECORD
