Metadata-Version: 2.4
Name: django-djanbee
Version: 0.1.0
Summary: A free command-line tool to simplify Django project deployment in production environments
Author-email: Djanbee Team <djanbee.team@gmail.com>
License: MIT
Project-URL: Homepage, https://github.com/Djanbee-team/django-djanbee
Project-URL: Repository, https://github.com/Djanbee-team/django-djanbee
Project-URL: Issues, https://github.com/Djanbee-team/django-djanbee/issues
Project-URL: Documentation, https://github.com/Djanbee-team/django-djanbee#readme
Keywords: django,deployment,nginx,gunicorn,production
Classifier: Development Status :: 3 - Alpha
Classifier: Intended Audience :: Developers
Classifier: License :: OSI Approved :: MIT License
Classifier: Programming Language :: Python :: 3
Classifier: Programming Language :: Python :: 3.6
Classifier: Programming Language :: Python :: 3.7
Classifier: Programming Language :: Python :: 3.8
Classifier: Programming Language :: Python :: 3.9
Classifier: Programming Language :: Python :: 3.10
Classifier: Programming Language :: Python :: 3.11
Classifier: Topic :: Software Development :: Build Tools
Classifier: Framework :: Django
Classifier: Topic :: System :: Systems Administration
Classifier: Topic :: Internet :: WWW/HTTP :: HTTP Servers
Requires-Python: >=3.6
License-File: LICENSE
Requires-Dist: django>=3.0
Requires-Dist: gunicorn>=20.0.0
Requires-Dist: python-dotenv
Requires-Dist: click
Dynamic: license-file
